CONTRIBUTING.rst
HISTORY.rst
LICENSE
MANIFEST.in
README.rst
resources.qrc
setup.py
./__init__.py
./clodsa.py
./labelGlandula.py
./postProcess.py
./postProcessPuntos.py
data/predefined_classes.txt
fichs/vocGlandula.names
fichs/yolov3Glandula.cfg
labelGlandula.egg-info/PKG-INFO
labelGlandula.egg-info/SOURCES.txt
labelGlandula.egg-info/dependency_links.txt
labelGlandula.egg-info/entry_points.txt
labelGlandula.egg-info/not-zip-safe
labelGlandula.egg-info/requires.txt
labelGlandula.egg-info/top_level.txt
libs/__init__.py
libs/canvas.py
libs/colorDialog.py
libs/constants.py
libs/excelDialog.py
libs/excelGlandula.py
libs/hashableQListWidgetItem.py
libs/labelDialog.py
libs/labelFile.py
libs/linea.py
libs/pascal_voc_io.py
libs/resources.py
libs/settings.py
libs/shape.py
libs/stringBundle.py
libs/toolBar.py
libs/ustr.py
libs/utils.py
libs/version.py
libs/yolo_io.py
libs/zoomWidget.py
notebooks/mainModel.py
notebooks/notebookYolo.py
notebooks/notebookmenu.py
notebooks/testTimeAugmentation.py
predict/detect.py
predict/detectGlandula.py
predict/generateExcel.py
predict/selectPesos.py
resources/strings/strings-zh-CN.properties
resources/strings/strings-zh-TW.properties
resources/strings/strings.properties