Metadata-Version: 1.2
Name: labelGlandula
Version: 0.5.2
Summary: labelGlandula is a graphical tool for using and creating detection models
Home-page: https://github.com/ancasag/labelGlandula
Author: Angela Casado
Author-email: angela.casado@unirioja.es
License: MIT license
Keywords: labelGlandula detection deeplearning
Platform: UNKNOWN
Classifier: Development Status :: 5 - Production/Stable
Classifier: Intended Audience :: Developers
Classifier: License :: OSI Approved :: MIT License
Classifier: Natural Language :: English
Classifier: Programming Language :: Python :: 3.6
Classifier: Programming Language :: Python :: 3.7
Requires-Python: >=3.0.0
